odoo/addons/account_financial_report_sale/README.rst
odoo/addons/account_financial_report_sale/__init__.py
odoo/addons/account_financial_report_sale/__manifest__.py
odoo/addons/account_financial_report_sale/i18n/account_financial_report_sale.pot
odoo/addons/account_financial_report_sale/i18n/es.po
odoo/addons/account_financial_report_sale/i18n/it.po
odoo/addons/account_financial_report_sale/i18n/pt_BR.po
odoo/addons/account_financial_report_sale/i18n/sl.po
odoo/addons/account_financial_report_sale/readme/CONTRIBUTORS.md
odoo/addons/account_financial_report_sale/readme/DESCRIPTION.md
odoo/addons/account_financial_report_sale/readme/USAGE.md
odoo/addons/account_financial_report_sale/report/__init__.py
odoo/addons/account_financial_report_sale/report/open_items.py
odoo/addons/account_financial_report_sale/static/description/icon.png
odoo/addons/account_financial_report_sale/static/description/index.html
odoo/addons/account_financial_report_sale/tests/__init__.py
odoo/addons/account_financial_report_sale/tests/test_open_items.py
odoo/addons/account_financial_report_sale/wizard/__init__.py
odoo/addons/account_financial_report_sale/wizard/open_items_wizard.py
odoo_addon_account_financial_report_sale-18.0.1.0.0.4.dist-info/METADATA
odoo_addon_account_financial_report_sale-18.0.1.0.0.4.dist-info/WHEEL
odoo_addon_account_financial_report_sale-18.0.1.0.0.4.dist-info/top_level.txt
odoo_addon_account_financial_report_sale-18.0.1.0.0.4.dist-info/RECORD
